nn4k/__init__.py
nn4k/consts/__init__.py
nn4k/executor/__init__.py
nn4k/executor/base.py
nn4k/executor/deepke.py
nn4k/executor/huggingface/__init__.py
nn4k/executor/huggingface/hf_decode_only_executor.py
nn4k/executor/huggingface/hf_embedding_executor.py
nn4k/executor/huggingface/nn_hf_trainer.py
nn4k/executor/huggingface/base/__init__.py
nn4k/executor/huggingface/base/hf_args.py
nn4k/executor/huggingface/base/hf_llm_executor.py
nn4k/executor/huggingface/default_config/__init__.py
nn4k/executor/huggingface/default_config/decodeonly/__init__.py
nn4k/executor/huggingface/default_config/decodeonly/env_init.sh
nn4k/executor/huggingface/default_config/decodeonly/local_infer.json5
nn4k/executor/huggingface/default_config/decodeonly/local_sft.json5
nn4k/executor/huggingface/default_config/decodeonly/task_entry.py
nn4k/invoker/__init__.py
nn4k/invoker/base.py
nn4k/invoker/hub_invoker.py
nn4k/invoker/openai.py
nn4k/invoker/default_config/remote_infer/remote_infer.json5
nn4k/invoker/default_config/remote_infer/remote_infer.py
nn4k/nnhub/__init__.py
nn4k/utils/__init__.py
nn4k/utils/args_utils.py
nn4k/utils/class_importing.py
nn4k/utils/config_parsing.py
nn4k/utils/invoker_checking.py
nn4k/utils/io/__init__.py
nn4k/utils/io/dataset_utils.py
nn4k/utils/io/file_utils.py
openspg_nn4k-0.0.3.dist-info/LICENSE
openspg_nn4k-0.0.3.dist-info/METADATA
openspg_nn4k-0.0.3.dist-info/WHEEL
openspg_nn4k-0.0.3.dist-info/top_level.txt
openspg_nn4k-0.0.3.dist-info/RECORD
