Metadata-Version: 2.1
Name: openspg-nn4k
Version: 0.0.3
Summary: nn4k
Home-page: https://github.com/OpenSPG/openspg
License: UNKNOWN
Platform: UNKNOWN
Requires-Python: >=3.8
License-File: LICENSE
Requires-Dist: openai
Requires-Dist: json5
